[
  {
    "id": 75209893,
    "clientId": 2092888,
    "providerId": 3149598,
    "pieceCid": {
      "/": "baga6ea4seaqfyam4mxkhkuqcya6aklrttzyvwyggrpj7gl47nftz4uwsbo5miby"
    },
    "pieceSize": 34359738368,
    "termMin": 1525000,
    "termMax": 1784200,
    "expiration": 4286075,
    "height": 4269524
  },
  {
    "id": 75209892,
    "clientId": 2092888,
    "providerId": 3149598,
    "pieceCid": {
      "/": "baga6ea4seaqngyfg6z7pdeejnnieq33idlt7ruceeg2jc4b4nmb4bpssaovugay"
    },
    "pieceSize": 34359738368,
    "termMin": 1525000,
    "termMax": 1784200,
    "expiration": 4286074,
    "height": 4269524
  },
  {
    "id": 75209891,
    "clientId": 2092888,
    "providerId": 3149598,
    "pieceCid": {
      "/": "baga6ea4seaqgtguk7w7qatbk2vetvi6a7da5lns3wf3eatsjeogcwjgujtlr2oa"
    },
    "pieceSize": 34359738368,
    "termMin": 1525000,
    "termMax": 1784200,
    "expiration": 4286074,
    "height": 4269524
  },
  {
    "id": 75209890,
    "clientId": 2092888,
    "providerId": 3149598,
    "pieceCid": {
      "/": "baga6ea4seaqjmvad6mixjr2aqwoctgoaykecmnjs7sdrzgrfhr4luxtfwd77gkq"
    },
    "pieceSize": 34359738368,
    "termMin": 1525000,
    "termMax": 1784200,
    "expiration": 4286074,
    "height": 4269524
  },
  {
    "id": 75210215,
    "clientId": 2092888,
    "providerId": 3149598,
    "pieceCid": {
      "/": "baga6ea4seaqjzd3znf3ihe6u5qugpo2ip3uhfi7d2yrmt3q4wrwil6wjoxkzsdi"
    },
    "pieceSize": 34359738368,
    "termMin": 1525000,
    "termMax": 1784200,
    "expiration": 4286076,
    "height": 4269531
  },
  {
    "id": 75210214,
    "clientId": 2092888,
    "providerId": 3149598,
    "pieceCid": {
      "/": "baga6ea4seaqfpiyolzz2h7glcugzqbaj4roh5rjxqy4gub667zqs64cmtjduygi"
    },
    "pieceSize": 34359738368,
    "termMin": 1525000,
    "termMax": 1784200,
    "expiration": 4286076,
    "height": 4269531
  },
  {
    "id": 75210213,
    "clientId": 2092888,
    "providerId": 3149598,
    "pieceCid": {
      "/": "baga6ea4seaqgeu263qgk6gs25tzk3y7huytbmrrvyeliazc4zrysafmggd2n2gy"
    },
    "pieceSize": 34359738368,
    "termMin": 1525000,
    "termMax": 1784200,
    "expiration": 4286075,
    "height": 4269531
  },
  {
    "id": 75210212,
    "clientId": 2092888,
    "providerId": 3149598,
    "pieceCid": {
      "/": "baga6ea4seaqgniw3addsxovtgievsjmjxykdy7vy2z2wadqlxnsd6jhjdtz5meq"
    },
    "pieceSize": 34359738368,
    "termMin": 1525000,
    "termMax": 1784200,
    "expiration": 4286075,
    "height": 4269531
  },
  {
    "id": 75210211,
    "clientId": 2092888,
    "providerId": 3149598,
    "pieceCid": {
      "/": "baga6ea4seaqhpl2bfkbsksmdkbtjdwmt2nmg6d33opovotk55zxejbg3jpgvgdi"
    },
    "pieceSize": 34359738368,
    "termMin": 1525000,
    "termMax": 1784200,
    "expiration": 4286078,
    "height": 4269531
  },
  {
    "id": 75210210,
    "clientId": 2092888,
    "providerId": 3149598,
    "pieceCid": {
      "/": "baga6ea4seaqijf2bpokmisaeox2bfyye4ukfhibdnwg7mg2a7jvmo6ht43ljsjy"
    },
    "pieceSize": 34359738368,
    "termMin": 1525000,
    "termMax": 1784200,
    "expiration": 4286078,
    "height": 4269531
  },
  {
    "id": 75210209,
    "clientId": 2092888,
    "providerId": 3149598,
    "pieceCid": {
      "/": "baga6ea4seaqlpjgk55i7accdi7oqeu3fvdaz5oeq5d433qwoueid422gkoynqfy"
    },
    "pieceSize": 34359738368,
    "termMin": 1525000,
    "termMax": 1784200,
    "expiration": 4286077,
    "height": 4269531
  },
  {
    "id": 75210208,
    "clientId": 2092888,
    "providerId": 3149598,
    "pieceCid": {
      "/": "baga6ea4seaqnd432xvwkqxeddolx74xxoji7zzocqsy26ktzm7koit5jfmkzaia"
    },
    "pieceSize": 34359738368,
    "termMin": 1525000,
    "termMax": 1784200,
    "expiration": 4286076,
    "height": 4269531
  },
  {
    "id": 75210784,
    "clientId": 2092888,
    "providerId": 3149598,
    "pieceCid": {
      "/": "baga6ea4seaqfsmino6vfyajcb2ohd4dhwb2x6yd25p2j4ilzwtakal7afhm6ueq"
    },
    "pieceSize": 34359738368,
    "termMin": 1525000,
    "termMax": 1784200,
    "expiration": 4286078,
    "height": 4269548
  },
  {
    "id": 75210783,
    "clientId": 2092888,
    "providerId": 3149598,
    "pieceCid": {
      "/": "baga6ea4seaql4yflggbb6b2ansjvgeciawhoqjyrzbcys4cch2urcgabw65baay"
    },
    "pieceSize": 34359738368,
    "termMin": 1525000,
    "termMax": 1784200,
    "expiration": 4286079,
    "height": 4269548
  },
  {
    "id": 75210782,
    "clientId": 2092888,
    "providerId": 3149598,
    "pieceCid": {
      "/": "baga6ea4seaqfm5dsahga2ul6dghwe6bhab2rrffa2574h626qriwsu5jlvfikfq"
    },
    "pieceSize": 34359738368,
    "termMin": 1525000,
    "termMax": 1784200,
    "expiration": 4286078,
    "height": 4269548
  },
  {
    "id": 75210781,
    "clientId": 2092888,
    "providerId": 3149598,
    "pieceCid": {
      "/": "baga6ea4seaqgguiu6447cyii7j4qsmod3pwosop2zg7jlwlzwqnn6tx36k4j2my"
    },
    "pieceSize": 34359738368,
    "termMin": 1525000,
    "termMax": 1784200,
    "expiration": 4286077,
    "height": 4269548
  },
  {
    "id": 75210780,
    "clientId": 2092888,
    "providerId": 3149598,
    "pieceCid": {
      "/": "baga6ea4seaqpminriumyfbt33ufh3pe4l7e4r6iedctggkaagbhmdhza3od3cmy"
    },
    "pieceSize": 34359738368,
    "termMin": 1525000,
    "termMax": 1784200,
    "expiration": 4286077,
    "height": 4269548
  },
  {
    "id": 75210779,
    "clientId": 2092888,
    "providerId": 3149598,
    "pieceCid": {
      "/": "baga6ea4seaqpq7tdv2hz4e6jeh65kw6xu7nvvd5x6a3brwgxudk66w2fqgxauaq"
    },
    "pieceSize": 34359738368,
    "termMin": 1525000,
    "termMax": 1784200,
    "expiration": 4286077,
    "height": 4269548
  },
  {
    "id": 75210778,
    "clientId": 2092888,
    "providerId": 3149598,
    "pieceCid": {
      "/": "baga6ea4seaqfjsobggyrwdcn5qtkciqg5e6cseqyo5yici65moomqdktgsriehy"
    },
    "pieceSize": 34359738368,
    "termMin": 1525000,
    "termMax": 1784200,
    "expiration": 4286076,
    "height": 4269548
  },
  {
    "id": 75210777,
    "clientId": 2092888,
    "providerId": 3149598,
    "pieceCid": {
      "/": "baga6ea4seaqc7tllatfhtwjqhvkbq6xsu77cgfyhvag3snvbdxegvatf6xlzaaq"
    },
    "pieceSize": 34359738368,
    "termMin": 1525000,
    "termMax": 1784200,
    "expiration": 4286075,
    "height": 4269548
  },
  {
    "id": 75211048,
    "clientId": 2092888,
    "providerId": 3149598,
    "pieceCid": {
      "/": "baga6ea4seaqn6kn7mawmssuntfolu7jng6d774ztv6y5rc4okbqm25mjwfmgkci"
    },
    "pieceSize": 34359738368,
    "termMin": 1525000,
    "termMax": 1784200,
    "expiration": 4286079,
    "height": 4269555
  },
  {
    "id": 75211047,
    "clientId": 2092888,
    "providerId": 3149598,
    "pieceCid": {
      "/": "baga6ea4seaqij5gv6py37dneeqeho32dmgjwa725pk3syzvykkcboz6lztlhcby"
    },
    "pieceSize": 34359738368,
    "termMin": 1525000,
    "termMax": 1784200,
    "expiration": 4286081,
    "height": 4269555
  },
  {
    "id": 75211046,
    "clientId": 2092888,
    "providerId": 3149598,
    "pieceCid": {
      "/": "baga6ea4seaqd2obpc5eqn2yw2x3z3eb43kt6l6ohq2delrl5v6djlwlklxlbcfq"
    },
    "pieceSize": 34359738368,
    "termMin": 1525000,
    "termMax": 1784200,
    "expiration": 4286080,
    "height": 4269555
  },
  {
    "id": 75211045,
    "clientId": 2092888,
    "providerId": 3149598,
    "pieceCid": {
      "/": "baga6ea4seaqbx7s3rs73dlbybiserjxxuaed6ivw5fdmt4nmndhdoadaygpkgia"
    },
    "pieceSize": 34359738368,
    "termMin": 1525000,
    "termMax": 1784200,
    "expiration": 4286080,
    "height": 4269555
  },
  {
    "id": 75211044,
    "clientId": 2092888,
    "providerId": 3149598,
    "pieceCid": {
      "/": "baga6ea4seaqeiz4j2bxqr5iduxowdymf4yt5jli24e77ntqhkfyfatzm37jy4jq"
    },
    "pieceSize": 34359738368,
    "termMin": 1525000,
    "termMax": 1784200,
    "expiration": 4286080,
    "height": 4269555
  },
  {
    "id": 75211043,
    "clientId": 2092888,
    "providerId": 3149598,
    "pieceCid": {
      "/": "baga6ea4seaqndxisqykj4q5alphi7h2jkgoswqb3ihht72okktk74fhk6rszcii"
    },
    "pieceSize": 34359738368,
    "termMin": 1525000,
    "termMax": 1784200,
    "expiration": 4286080,
    "height": 4269555
  },
  {
    "id": 75211042,
    "clientId": 2092888,
    "providerId": 3149598,
    "pieceCid": {
      "/": "baga6ea4seaqapmoafgr7gmmy3zob4hivaxq56t7dubauctjiuzxeavsdmp5hghy"
    },
    "pieceSize": 34359738368,
    "termMin": 1525000,
    "termMax": 1784200,
    "expiration": 4286079,
    "height": 4269555
  },
  {
    "id": 75211041,
    "clientId": 2092888,
    "providerId": 3149598,
    "pieceCid": {
      "/": "baga6ea4seaqiuo3lxdoxtccpsfrqidflqourcjlhfz3zws67dvhdbpolzssa6nq"
    },
    "pieceSize": 34359738368,
    "termMin": 1525000,
    "termMax": 1784200,
    "expiration": 4286079,
    "height": 4269555
  },
  {
    "id": 75212045,
    "clientId": 2092888,
    "providerId": 3149598,
    "pieceCid": {
      "/": "baga6ea4seaqg77hbuvwjvj2brkb2p2xztvbjdf6itd6wydn3ksvputsglcx3ojq"
    },
    "pieceSize": 34359738368,
    "termMin": 1525000,
    "termMax": 1784200,
    "expiration": 4286082,
    "height": 4269585
  },
  {
    "id": 75212044,
    "clientId": 2092888,
    "providerId": 3149598,
    "pieceCid": {
      "/": "baga6ea4seaqmtv5eot2rrg7m7cbq6szy7aobftoc7azzkdkhymf4vkvddymbyoa"
    },
    "pieceSize": 34359738368,
    "termMin": 1525000,
    "termMax": 1784200,
    "expiration": 4286081,
    "height": 4269585
  },
  {
    "id": 75212043,
    "clientId": 2092888,
    "providerId": 3149598,
    "pieceCid": {
      "/": "baga6ea4seaqbb4wfke2vqkvpzrsinqojdjtpjlvunwgax3azrswgnqexljwwani"
    },
    "pieceSize": 34359738368,
    "termMin": 1525000,
    "termMax": 1784200,
    "expiration": 4286082,
    "height": 4269585
  },
  {
    "id": 75212042,
    "clientId": 2092888,
    "providerId": 3149598,
    "pieceCid": {
      "/": "baga6ea4seaqbr6puay52rv6ref4w5xfm3fnkb6gburmdlnzpcbeawjil2ks2qbi"
    },
    "pieceSize": 34359738368,
    "termMin": 1525000,
    "termMax": 1784200,
    "expiration": 4286080,
    "height": 4269585
  },
  {
    "id": 75212041,
    "clientId": 2092888,
    "providerId": 3149598,
    "pieceCid": {
      "/": "baga6ea4seaqex2a7sio3ghibznllvpk3jfmde4l7zmau3guw7o3naou2dsut2gi"
    },
    "pieceSize": 34359738368,
    "termMin": 1525000,
    "termMax": 1784200,
    "expiration": 4286081,
    "height": 4269585
  },
  {
    "id": 75212040,
    "clientId": 2092888,
    "providerId": 3149598,
    "pieceCid": {
      "/": "baga6ea4seaqfutwovfytlvjlmdm2ebfnw3zjxw4m3e3bfbkfficauaqzv6arymy"
    },
    "pieceSize": 34359738368,
    "termMin": 1525000,
    "termMax": 1784200,
    "expiration": 4286081,
    "height": 4269585
  },
  {
    "id": 75212039,
    "clientId": 2092888,
    "providerId": 3149598,
    "pieceCid": {
      "/": "baga6ea4seaqmee63xjufqb43wonb4dbtz6ptiu5xqr6e6ielymzxdsblwodiybi"
    },
    "pieceSize": 34359738368,
    "termMin": 1525000,
    "termMax": 1784200,
    "expiration": 4286083,
    "height": 4269585
  },
  {
    "id": 75212038,
    "clientId": 2092888,
    "providerId": 3149598,
    "pieceCid": {
      "/": "baga6ea4seaqigx5jw25nizd5umo3iz4ui7zu436edsipzakrg633myjjc5fradq"
    },
    "pieceSize": 34359738368,
    "termMin": 1525000,
    "termMax": 1784200,
    "expiration": 4286082,
    "height": 4269585
  },
  {
    "id": 75212686,
    "clientId": 2092888,
    "providerId": 3149598,
    "pieceCid": {
      "/": "baga6ea4seaqhtww5hubqkxqs2tqcjqwfz2vvkp2jhay64hv44rmy2ud3ezhr6cq"
    },
    "pieceSize": 34359738368,
    "termMin": 1525000,
    "termMax": 1784200,
    "expiration": 4286083,
    "height": 4269607
  },
  {
    "id": 75212685,
    "clientId": 2092888,
    "providerId": 3149598,
    "pieceCid": {
      "/": "baga6ea4seaqj3fp5grze3tnfc6zrqup52kib6aulsvvlqs3nfdhzp7rwiqtjihq"
    },
    "pieceSize": 34359738368,
    "termMin": 1525000,
    "termMax": 1784200,
    "expiration": 4286082,
    "height": 4269607
  },
  {
    "id": 75212684,
    "clientId": 2092888,
    "providerId": 3149598,
    "pieceCid": {
      "/": "baga6ea4seaqprdzktpn2i6juozylns2cssgewlm3dehbdanxp633tqc5fdsomaq"
    },
    "pieceSize": 34359738368,
    "termMin": 1525000,
    "termMax": 1784200,
    "expiration": 4286085,
    "height": 4269607
  },
  {
    "id": 75212683,
    "clientId": 2092888,
    "providerId": 3149598,
    "pieceCid": {
      "/": "baga6ea4seaqbr3rzqokwkpzmptgfudyyt6ehvbtf5jlpv7hi2b2mi3qi54b4yea"
    },
    "pieceSize": 34359738368,
    "termMin": 1525000,
    "termMax": 1784200,
    "expiration": 4286083,
    "height": 4269607
  },
  {
    "id": 75212682,
    "clientId": 2092888,
    "providerId": 3149598,
    "pieceCid": {
      "/": "baga6ea4seaqkqri5gcj7xv4gz6acy62ox3vj4uybdt6mzh2zcnw6yxwmnuk7qay"
    },
    "pieceSize": 34359738368,
    "termMin": 1525000,
    "termMax": 1784200,
    "expiration": 4286085,
    "height": 4269607
  },
  {
    "id": 75212681,
    "clientId": 2092888,
    "providerId": 3149598,
    "pieceCid": {
      "/": "baga6ea4seaqpucurl7xav7peqowunmfj6zgjyfth3gtmzydwjwi7oms7nshb4iy"
    },
    "pieceSize": 34359738368,
    "termMin": 1525000,
    "termMax": 1784200,
    "expiration": 4286084,
    "height": 4269607
  },
  {
    "id": 75212680,
    "clientId": 2092888,
    "providerId": 3149598,
    "pieceCid": {
      "/": "baga6ea4seaqjfz4ynmq6lcoyolflyslawqf2gonwsjw37v2kcxwcxvtb4hccamq"
    },
    "pieceSize": 34359738368,
    "termMin": 1525000,
    "termMax": 1784200,
    "expiration": 4286084,
    "height": 4269607
  },
  {
    "id": 75212679,
    "clientId": 2092888,
    "providerId": 3149598,
    "pieceCid": {
      "/": "baga6ea4seaqh2zl6hr3ryp36jle32h2k3o7xtpfjup5t3j3oktfo4mh2ge6lyoi"
    },
    "pieceSize": 34359738368,
    "termMin": 1525000,
    "termMax": 1784200,
    "expiration": 4286083,
    "height": 4269607
  },
  {
    "id": 75213372,
    "clientId": 2092888,
    "providerId": 3149598,
    "pieceCid": {
      "/": "baga6ea4seaqdwwrqldkfz5afatjavzilca2qd5ssymovfqwcbm4r4vpi5xol4ga"
    },
    "pieceSize": 34359738368,
    "termMin": 1525000,
    "termMax": 1784200,
    "expiration": 4286088,
    "height": 4269626
  },
  {
    "id": 75213371,
    "clientId": 2092888,
    "providerId": 3149598,
    "pieceCid": {
      "/": "baga6ea4seaqdwwmj43u3zykgec6mqdzxydx4wbheyesgq7fxnmrjqlltexi4afi"
    },
    "pieceSize": 34359738368,
    "termMin": 1525000,
    "termMax": 1784200,
    "expiration": 4286087,
    "height": 4269626
  },
  {
    "id": 75213370,
    "clientId": 2092888,
    "providerId": 3149598,
    "pieceCid": {
      "/": "baga6ea4seaqdz5wvyglm57pwrja7eithcshgyiatefqtclyz2l74jriacd7nelq"
    },
    "pieceSize": 34359738368,
    "termMin": 1525000,
    "termMax": 1784200,
    "expiration": 4286086,
    "height": 4269626
  },
  {
    "id": 75213369,
    "clientId": 2092888,
    "providerId": 3149598,
    "pieceCid": {
      "/": "baga6ea4seaqj755e52egqb55qky2kdokmvjzf6nkjaa76cnq2kjgjyzuyooukey"
    },
    "pieceSize": 34359738368,
    "termMin": 1525000,
    "termMax": 1784200,
    "expiration": 4286086,
    "height": 4269626
  },
  {
    "id": 75213368,
    "clientId": 2092888,
    "providerId": 3149598,
    "pieceCid": {
      "/": "baga6ea4seaqexvhprjmrqdhjgi6g6ikcjynnhfxmi37gx4kxm42lsgfzfdqvoga"
    },
    "pieceSize": 34359738368,
    "termMin": 1525000,
    "termMax": 1784200,
    "expiration": 4286085,
    "height": 4269626
  },
  {
    "id": 75213367,
    "clientId": 2092888,
    "providerId": 3149598,
    "pieceCid": {
      "/": "baga6ea4seaqnr5iwrvhypgpnbs67az43ok24idvr32n2jwrynj2poptuc447omq"
    },
    "pieceSize": 34359738368,
    "termMin": 1525000,
    "termMax": 1784200,
    "expiration": 4286089,
    "height": 4269626
  },
  {
    "id": 75213366,
    "clientId": 2092888,
    "providerId": 3149598,
    "pieceCid": {
      "/": "baga6ea4seaqjophrmb4gfdbyunoown24kowokskfjl63s2dzddggp47iysdkggy"
    },
    "pieceSize": 34359738368,
    "termMin": 1525000,
    "termMax": 1784200,
    "expiration": 4286089,
    "height": 4269626
  },
  {
    "id": 75213365,
    "clientId": 2092888,
    "providerId": 3149598,
    "pieceCid": {
      "/": "baga6ea4seaqayccqdgrgrzremlswli5nrf232zdf7klohwx3jrhunuf7qhimsla"
    },
    "pieceSize": 34359738368,
    "termMin": 1525000,
    "termMax": 1784200,
    "expiration": 4286088,
    "height": 4269626
  },
  {
    "id": 75214017,
    "clientId": 2092888,
    "providerId": 3149598,
    "pieceCid": {
      "/": "baga6ea4seaqetghcpeifb4ucuestr35wu2a4rbbjdy7j5o64mczlioslipo3gly"
    },
    "pieceSize": 34359738368,
    "termMin": 1525000,
    "termMax": 1784200,
    "expiration": 4286085,
    "height": 4269647
  },
  {
    "id": 75214016,
    "clientId": 2092888,
    "providerId": 3149598,
    "pieceCid": {
      "/": "baga6ea4seaqo2oerms7f626wunfvf2r67joclkaffmekidhfs3o754acxoqscdq"
    },
    "pieceSize": 34359738368,
    "termMin": 1525000,
    "termMax": 1784200,
    "expiration": 4286084,
    "height": 4269647
  },
  {
    "id": 75214015,
    "clientId": 2092888,
    "providerId": 3149598,
    "pieceCid": {
      "/": "baga6ea4seaqn6afynomnafiy24xspmdfdl4pyvp3q6rc7lcbm57fov5bqoiumcy"
    },
    "pieceSize": 34359738368,
    "termMin": 1525000,
    "termMax": 1784200,
    "expiration": 4286090,
    "height": 4269647
  },
  {
    "id": 75214014,
    "clientId": 2092888,
    "providerId": 3149598,
    "pieceCid": {
      "/": "baga6ea4seaqfuyc7n5gzw7j33czexaogbdgmw3nmagdttaga4naczjs35v274gq"
    },
    "pieceSize": 34359738368,
    "termMin": 1525000,
    "termMax": 1784200,
    "expiration": 4286090,
    "height": 4269647
  },
  {
    "id": 75214013,
    "clientId": 2092888,
    "providerId": 3149598,
    "pieceCid": {
      "/": "baga6ea4seaqaxz5qlegokvhwit2k7h34yzcbll3mkrmlsasir643nmojruykkhy"
    },
    "pieceSize": 34359738368,
    "termMin": 1525000,
    "termMax": 1784200,
    "expiration": 4286087,
    "height": 4269647
  },
  {
    "id": 75214012,
    "clientId": 2092888,
    "providerId": 3149598,
    "pieceCid": {
      "/": "baga6ea4seaqhsgjxun3r2xmvk7gji5yovo6y2xk56fgdpwfpdzorsbuxs4amccy"
    },
    "pieceSize": 34359738368,
    "termMin": 1525000,
    "termMax": 1784200,
    "expiration": 4286087,
    "height": 4269647
  },
  {
    "id": 75214011,
    "clientId": 2092888,
    "providerId": 3149598,
    "pieceCid": {
      "/": "baga6ea4seaqc3eskmnxjlc2uy2n5rftnn52tnqjmpedgwpkmerripkhquy2zgpq"
    },
    "pieceSize": 34359738368,
    "termMin": 1525000,
    "termMax": 1784200,
    "expiration": 4286086,
    "height": 4269647
  },
  {
    "id": 75214010,
    "clientId": 2092888,
    "providerId": 3149598,
    "pieceCid": {
      "/": "baga6ea4seaqbej3m4l22afzumwhmh2c733y5nov2feifmdysxzdmqpwyt5vnycq"
    },
    "pieceSize": 34359738368,
    "termMin": 1525000,
    "termMax": 1784200,
    "expiration": 4286086,
    "height": 4269647
  },
  {
    "id": 75214421,
    "clientId": 2092888,
    "providerId": 3149598,
    "pieceCid": {
      "/": "baga6ea4seaqd7xiyf37tcua3quk4l2onlyg2tbnxxk2uuirxsfvxuxez2bleagi"
    },
    "pieceSize": 34359738368,
    "termMin": 1525000,
    "termMax": 1784200,
    "expiration": 4286091,
    "height": 4269664
  },
  {
    "id": 75214420,
    "clientId": 2092888,
    "providerId": 3149598,
    "pieceCid": {
      "/": "baga6ea4seaqhcwvbs22whcgmevr7ixjij6yqlu6mzfdf24gtlobtwr6apx6seca"
    },
    "pieceSize": 34359738368,
    "termMin": 1525000,
    "termMax": 1784200,
    "expiration": 4286089,
    "height": 4269664
  },
  {
    "id": 75214419,
    "clientId": 2092888,
    "providerId": 3149598,
    "pieceCid": {
      "/": "baga6ea4seaqmc6lnxclq5lzi6f2orqf3ui6b7ng4h3d3wr7lkp5aoamo7j4pqaa"
    },
    "pieceSize": 34359738368,
    "termMin": 1525000,
    "termMax": 1784200,
    "expiration": 4286089,
    "height": 4269664
  },
  {
    "id": 75214418,
    "clientId": 2092888,
    "providerId": 3149598,
    "pieceCid": {
      "/": "baga6ea4seaqnyyi5yha5274fz4e2d7bzo42pdgyvu4qk6tlpbrirkojaergkmiq"
    },
    "pieceSize": 34359738368,
    "termMin": 1525000,
    "termMax": 1784200,
    "expiration": 4286088,
    "height": 4269664
  },
  {
    "id": 75214417,
    "clientId": 2092888,
    "providerId": 3149598,
    "pieceCid": {
      "/": "baga6ea4seaqbbjbqb75zxotd3sbls4enzzb3nonqj26fnaoxb3dl5rakfn4a2gi"
    },
    "pieceSize": 34359738368,
    "termMin": 1525000,
    "termMax": 1784200,
    "expiration": 4286088,
    "height": 4269664
  },
  {
    "id": 75214416,
    "clientId": 2092888,
    "providerId": 3149598,
    "pieceCid": {
      "/": "baga6ea4seaqmjc2le4lgf6x3mvlinwxwhqzffqkgqz2lacyg2izbre4qosyz4da"
    },
    "pieceSize": 34359738368,
    "termMin": 1525000,
    "termMax": 1784200,
    "expiration": 4286087,
    "height": 4269664
  },
  {
    "id": 75214415,
    "clientId": 2092888,
    "providerId": 3149598,
    "pieceCid": {
      "/": "baga6ea4seaqjyh3w6h6fncorlwrsdlouvm3cvftdcqgsi2p6p26iukspsywogoy"
    },
    "pieceSize": 34359738368,
    "termMin": 1525000,
    "termMax": 1784200,
    "expiration": 4286091,
    "height": 4269664
  },
  {
    "id": 75214414,
    "clientId": 2092888,
    "providerId": 3149598,
    "pieceCid": {
      "/": "baga6ea4seaqezhtljxlz6gqksrh5phfeflbbuxjpjeamqn2nnypaqn22aa33ica"
    },
    "pieceSize": 34359738368,
    "termMin": 1525000,
    "termMax": 1784200,
    "expiration": 4286090,
    "height": 4269664
  },
  {
    "id": 75215002,
    "clientId": 2092888,
    "providerId": 3149598,
    "pieceCid": {
      "/": "baga6ea4seaqb44kzbnim3wmsw2aphqpndjz33a3gqwriogtnuufg2mvqoslfeiy"
    },
    "pieceSize": 34359738368,
    "termMin": 1525000,
    "termMax": 1784200,
    "expiration": 4286093,
    "height": 4269686
  },
  {
    "id": 75215001,
    "clientId": 2092888,
    "providerId": 3149598,
    "pieceCid": {
      "/": "baga6ea4seaqc4xyyvljn6jx2y62jej5dtqzmdlpl22wz2gcuvevpaqgybr24siq"
    },
    "pieceSize": 34359738368,
    "termMin": 1525000,
    "termMax": 1784200,
    "expiration": 4286092,
    "height": 4269686
  },
  {
    "id": 75215000,
    "clientId": 2092888,
    "providerId": 3149598,
    "pieceCid": {
      "/": "baga6ea4seaqpeycq2clk3bdw53lthltmauknzggxemsanwdkyo3svuk2hqgjkeq"
    },
    "pieceSize": 34359738368,
    "termMin": 1525000,
    "termMax": 1784200,
    "expiration": 4286092,
    "height": 4269686
  },
  {
    "id": 75214999,
    "clientId": 2092888,
    "providerId": 3149598,
    "pieceCid": {
      "/": "baga6ea4seaqmdz3vi7v7ganzekiy2fftlssycjhxto6ryrloysbtcseqbkxucla"
    },
    "pieceSize": 34359738368,
    "termMin": 1525000,
    "termMax": 1784200,
    "expiration": 4286091,
    "height": 4269686
  },
  {
    "id": 75214998,
    "clientId": 2092888,
    "providerId": 3149598,
    "pieceCid": {
      "/": "baga6ea4seaqm2vq6vze4jr3uwph4smzdghce6dk7kt6odx6vweqmvkkhd33ssea"
    },
    "pieceSize": 34359738368,
    "termMin": 1525000,
    "termMax": 1784200,
    "expiration": 4286090,
    "height": 4269686
  },
  {
    "id": 75214997,
    "clientId": 2092888,
    "providerId": 3149598,
    "pieceCid": {
      "/": "baga6ea4seaqauvuh4fnqtzrrff6nkrylc7k7lhq77suxm4pp72ovkvj76yw7yki"
    },
    "pieceSize": 34359738368,
    "termMin": 1525000,
    "termMax": 1784200,
    "expiration": 4286092,
    "height": 4269686
  },
  {
    "id": 75214996,
    "clientId": 2092888,
    "providerId": 3149598,
    "pieceCid": {
      "/": "baga6ea4seaqimu4vcfhpvpibgeg56fiyq6fwhqp6ajgv25cytaj55slaamp2sfy"
    },
    "pieceSize": 34359738368,
    "termMin": 1525000,
    "termMax": 1784200,
    "expiration": 4286092,
    "height": 4269686
  },
  {
    "id": 75214995,
    "clientId": 2092888,
    "providerId": 3149598,
    "pieceCid": {
      "/": "baga6ea4seaqj2gdj6iu3yz44txzfihx72r3dqh4usab5powuxofr526fjnq7ehi"
    },
    "pieceSize": 34359738368,
    "termMin": 1525000,
    "termMax": 1784200,
    "expiration": 4286091,
    "height": 4269686
  },
  {
    "id": 75215411,
    "clientId": 2092888,
    "providerId": 3149598,
    "pieceCid": {
      "/": "baga6ea4seaqdy2ooc625cvb7tdahezoruvofyvhympdqdqhagywc3upxn5vkmjq"
    },
    "pieceSize": 34359738368,
    "termMin": 1525000,
    "termMax": 1784200,
    "expiration": 4286095,
    "height": 4269703
  },
  {
    "id": 75215410,
    "clientId": 2092888,
    "providerId": 3149598,
    "pieceCid": {
      "/": "baga6ea4seaqnnvdwx7p3xnu2uxq4t2go5x6abv7isyeybqdq5kycibubrn57ony"
    },
    "pieceSize": 34359738368,
    "termMin": 1525000,
    "termMax": 1784200,
    "expiration": 4286094,
    "height": 4269703
  },
  {
    "id": 75215409,
    "clientId": 2092888,
    "providerId": 3149598,
    "pieceCid": {
      "/": "baga6ea4seaqk6ck7c2vqlnskmjea6vb2zw7fgsyxyzzvfbglhezm326fcqhgqmi"
    },
    "pieceSize": 34359738368,
    "termMin": 1525000,
    "termMax": 1784200,
    "expiration": 4286096,
    "height": 4269703
  },
  {
    "id": 75215408,
    "clientId": 2092888,
    "providerId": 3149598,
    "pieceCid": {
      "/": "baga6ea4seaqebrdyi7hxuycveulistgdgsxkc2ytjqcsf2c5v5ww274xxwgggby"
    },
    "pieceSize": 34359738368,
    "termMin": 1525000,
    "termMax": 1784200,
    "expiration": 4286094,
    "height": 4269703
  },
  {
    "id": 75215407,
    "clientId": 2092888,
    "providerId": 3149598,
    "pieceCid": {
      "/": "baga6ea4seaqpxxrgakvnuujbnxkq6ep7u6zfqktmr2cvbmpg7teecfhgmhgvkea"
    },
    "pieceSize": 34359738368,
    "termMin": 1525000,
    "termMax": 1784200,
    "expiration": 4286094,
    "height": 4269703
  },
  {
    "id": 75215406,
    "clientId": 2092888,
    "providerId": 3149598,
    "pieceCid": {
      "/": "baga6ea4seaqffptltqqdja3mzckzeqxurvsxe2suv6zhndaebi34hajj4mwbwfq"
    },
    "pieceSize": 34359738368,
    "termMin": 1525000,
    "termMax": 1784200,
    "expiration": 4286094,
    "height": 4269703
  },
  {
    "id": 75215405,
    "clientId": 2092888,
    "providerId": 3149598,
    "pieceCid": {
      "/": "baga6ea4seaqcrf7csqewz7s4zpk33gngiuolbu4nk3jsj473o2bvh5mjj7b36bi"
    },
    "pieceSize": 34359738368,
    "termMin": 1525000,
    "termMax": 1784200,
    "expiration": 4286093,
    "height": 4269703
  },
  {
    "id": 75215404,
    "clientId": 2092888,
    "providerId": 3149598,
    "pieceCid": {
      "/": "baga6ea4seaqjibetsptx6nvblwtql4n2jh6iu2nssac6qec3o3suja5qtkwsidq"
    },
    "pieceSize": 34359738368,
    "termMin": 1525000,
    "termMax": 1784200,
    "expiration": 4286093,
    "height": 4269703
  },
  {
    "id": 75215988,
    "clientId": 2092888,
    "providerId": 3149598,
    "pieceCid": {
      "/": "baga6ea4seaqmtzg44fg5rkcqetabvgztadyg27ql5rz6vew5voumh7qiona5efq"
    },
    "pieceSize": 34359738368,
    "termMin": 1525000,
    "termMax": 1784200,
    "expiration": 4286098,
    "height": 4269723
  },
  {
    "id": 75215987,
    "clientId": 2092888,
    "providerId": 3149598,
    "pieceCid": {
      "/": "baga6ea4seaqlosvldfzpv6hokgwzpf2fehdmg7ucx3jznvgjcj2nguekxmxhody"
    },
    "pieceSize": 34359738368,
    "termMin": 1525000,
    "termMax": 1784200,
    "expiration": 4286097,
    "height": 4269723
  },
  {
    "id": 75215986,
    "clientId": 2092888,
    "providerId": 3149598,
    "pieceCid": {
      "/": "baga6ea4seaqac7leey4gsyrxl5vjopq3qnltnerkd6poj7yeomfzxrpc46f64ea"
    },
    "pieceSize": 34359738368,
    "termMin": 1525000,
    "termMax": 1784200,
    "expiration": 4286097,
    "height": 4269723
  },
  {
    "id": 75215985,
    "clientId": 2092888,
    "providerId": 3149598,
    "pieceCid": {
      "/": "baga6ea4seaqc2ktc26kde4yy6uiia6qcek7wxcmi2sjznd3t7c26budq5jz3ily"
    },
    "pieceSize": 34359738368,
    "termMin": 1525000,
    "termMax": 1784200,
    "expiration": 4286096,
    "height": 4269723
  },
  {
    "id": 75215984,
    "clientId": 2092888,
    "providerId": 3149598,
    "pieceCid": {
      "/": "baga6ea4seaqcilklgr6t3maccomlqyz2gezimv43qn55s4wah5hjmwfgj564qdy"
    },
    "pieceSize": 34359738368,
    "termMin": 1525000,
    "termMax": 1784200,
    "expiration": 4286096,
    "height": 4269723
  },
  {
    "id": 75215983,
    "clientId": 2092888,
    "providerId": 3149598,
    "pieceCid": {
      "/": "baga6ea4seaqbj6i7izbn3fhfahoxypbrhwevbcf22spynbmbkcwquaxa7rd5goa"
    },
    "pieceSize": 34359738368,
    "termMin": 1525000,
    "termMax": 1784200,
    "expiration": 4286095,
    "height": 4269723
  },
  {
    "id": 75215982,
    "clientId": 2092888,
    "providerId": 3149598,
    "pieceCid": {
      "/": "baga6ea4seaqahgvc6dcuurpdysmfitbgjrp4iwoyywakpc6k7c6xzzayxl4tsbq"
    },
    "pieceSize": 34359738368,
    "termMin": 1525000,
    "termMax": 1784200,
    "expiration": 4286097,
    "height": 4269723
  },
  {
    "id": 75215981,
    "clientId": 2092888,
    "providerId": 3149598,
    "pieceCid": {
      "/": "baga6ea4seaqflk5cgkc3cttk75eihejhkhrgpescbmn3ryu4m7ujptrjkz5seli"
    },
    "pieceSize": 34359738368,
    "termMin": 1525000,
    "termMax": 1784200,
    "expiration": 4286095,
    "height": 4269723
  },
  {
    "id": 75216505,
    "clientId": 2092888,
    "providerId": 3149598,
    "pieceCid": {
      "/": "baga6ea4seaqoibkrncmw5h7fkl7etxni7xffzjppmaccudyk2wiwpleb4eiquja"
    },
    "pieceSize": 34359738368,
    "termMin": 1525000,
    "termMax": 1784200,
    "expiration": 4286099,
    "height": 4269746
  },
  {
    "id": 75216504,
    "clientId": 2092888,
    "providerId": 3149598,
    "pieceCid": {
      "/": "baga6ea4seaqdtof5yx3y6bh46rc4tlxygdhkae6eb53cpxmyjwwt7wewll7ikiy"
    },
    "pieceSize": 34359738368,
    "termMin": 1525000,
    "termMax": 1784200,
    "expiration": 4286098,
    "height": 4269746
  },
  {
    "id": 75216503,
    "clientId": 2092888,
    "providerId": 3149598,
    "pieceCid": {
      "/": "baga6ea4seaqdl7u4ib2gxqna2b3hsvqd3jf3uhrdleqj2jd35lizsha44ioxgcq"
    },
    "pieceSize": 34359738368,
    "termMin": 1525000,
    "termMax": 1784200,
    "expiration": 4286095,
    "height": 4269746
  },
  {
    "id": 75216502,
    "clientId": 2092888,
    "providerId": 3149598,
    "pieceCid": {
      "/": "baga6ea4seaqohzkbdsyq7d3efewaxayzuzm3nwvmdfn6lwfvhyvx7upwo7tvapi"
    },
    "pieceSize": 34359738368,
    "termMin": 1525000,
    "termMax": 1784200,
    "expiration": 4286099,
    "height": 4269746
  },
  {
    "id": 75216501,
    "clientId": 2092888,
    "providerId": 3149598,
    "pieceCid": {
      "/": "baga6ea4seaqhigkswwvgujf433e4qu4gtvi34bwrma4hfxfmd25zyihyu26ueea"
    },
    "pieceSize": 34359738368,
    "termMin": 1525000,
    "termMax": 1784200,
    "expiration": 4286098,
    "height": 4269746
  },
  {
    "id": 75216500,
    "clientId": 2092888,
    "providerId": 3149598,
    "pieceCid": {
      "/": "baga6ea4seaqdxajq7pdgrljrt6ggnhrc4ssuiinzqoaog5zm333qlsbhzjxgihy"
    },
    "pieceSize": 34359738368,
    "termMin": 1525000,
    "termMax": 1784200,
    "expiration": 4286097,
    "height": 4269746
  },
  {
    "id": 75216499,
    "clientId": 2092888,
    "providerId": 3149598,
    "pieceCid": {
      "/": "baga6ea4seaqi7vgr3dy4oum4lob2wdeicpwpn7zblra222lnbgu5vm6tayohchi"
    },
    "pieceSize": 34359738368,
    "termMin": 1525000,
    "termMax": 1784200,
    "expiration": 4286101,
    "height": 4269746
  },
  {
    "id": 75216498,
    "clientId": 2092888,
    "providerId": 3149598,
    "pieceCid": {
      "/": "baga6ea4seaqhmzcdeukfjc35456qmi542i7tf3mz4jwcw6c7jt3q2hopsgqbwky"
    },
    "pieceSize": 34359738368,
    "termMin": 1525000,
    "termMax": 1784200,
    "expiration": 4286100,
    "height": 4269746
  },
  {
    "id": 75216990,
    "clientId": 2092888,
    "providerId": 3149598,
    "pieceCid": {
      "/": "baga6ea4seaqa3e3t6lgajtsxybrj2jgwwpgw6e4jrehiswpnxlei262jbiyocki"
    },
    "pieceSize": 34359738368,
    "termMin": 1525000,
    "termMax": 1784200,
    "expiration": 4286101,
    "height": 4269769
  },
  {
    "id": 75216989,
    "clientId": 2092888,
    "providerId": 3149598,
    "pieceCid": {
      "/": "baga6ea4seaqmydowfjhyb77t6vq5pjwkys3fkqppgy23bjiisek3tx73jumradq"
    },
    "pieceSize": 34359738368,
    "termMin": 1525000,
    "termMax": 1784200,
    "expiration": 4286101,
    "height": 4269769
  },
  {
    "id": 75216988,
    "clientId": 2092888,
    "providerId": 3149598,
    "pieceCid": {
      "/": "baga6ea4seaqc7meqhbdvkhqoha5isnen5yzjtwfybekwnsxy2lmjqecckuxzuey"
    },
    "pieceSize": 34359738368,
    "termMin": 1525000,
    "termMax": 1784200,
    "expiration": 4286100,
    "height": 4269769
  },
  {
    "id": 75216987,
    "clientId": 2092888,
    "providerId": 3149598,
    "pieceCid": {
      "/": "baga6ea4seaqglxzkgpcrgwtgbff3fyjawi47ajey4qls4ovll4mbcm2xxy2l4aq"
    },
    "pieceSize": 34359738368,
    "termMin": 1525000,
    "termMax": 1784200,
    "expiration": 4286100,
    "height": 4269769
  },
  {
    "id": 75216986,
    "clientId": 2092888,
    "providerId": 3149598,
    "pieceCid": {
      "/": "baga6ea4seaqhtenb6lpk3lae4kaarbao55r6oltp6e2x3qeta6g2y35hvgiusii"
    },
    "pieceSize": 34359738368,
    "termMin": 1525000,
    "termMax": 1784200,
    "expiration": 4286100,
    "height": 4269769
  },
  {
    "id": 75216985,
    "clientId": 2092888,
    "providerId": 3149598,
    "pieceCid": {
      "/": "baga6ea4seaqbwt5iv6vqwxbughp6ejvqhx3ygt6v6cerrzcoghqefahmzdngqmy"
    },
    "pieceSize": 34359738368,
    "termMin": 1525000,
    "termMax": 1784200,
    "expiration": 4286099,
    "height": 4269769
  },
  {
    "id": 75216984,
    "clientId": 2092888,
    "providerId": 3149598,
    "pieceCid": {
      "/": "baga6ea4seaqakbe47bfkfy2y7l2og4qetcyuop4wqj53kdppgqr4uezjaf2laeq"
    },
    "pieceSize": 34359738368,
    "termMin": 1525000,
    "termMax": 1784200,
    "expiration": 4286099,
    "height": 4269769
  },
  {
    "id": 75216983,
    "clientId": 2092888,
    "providerId": 3149598,
    "pieceCid": {
      "/": "baga6ea4seaqadp5yootdtxn4vww3ftlq4hatt6setptetsbbu6rcgzl25db4egy"
    },
    "pieceSize": 34359738368,
    "termMin": 1525000,
    "termMax": 1784200,
    "expiration": 4286098,
    "height": 4269769
  },
  {
    "id": 75217408,
    "clientId": 2092888,
    "providerId": 3149598,
    "pieceCid": {
      "/": "baga6ea4seaqhwco75ajxez42dtiwztfwn25mbmfv3v4seeuklemau2mcgrorqiq"
    },
    "pieceSize": 34359738368,
    "termMin": 1525000,
    "termMax": 1784200,
    "expiration": 4286104,
    "height": 4269784
  },
  {
    "id": 75217407,
    "clientId": 2092888,
    "providerId": 3149598,
    "pieceCid": {
      "/": "baga6ea4seaqd7jlni63ahekwpssesx6u72gvlmznkhiu6oydnkwaqlkse33j4ei"
    },
    "pieceSize": 34359738368,
    "termMin": 1525000,
    "termMax": 1784200,
    "expiration": 4286103,
    "height": 4269784
  },
  {
    "id": 75217406,
    "clientId": 2092888,
    "providerId": 3149598,
    "pieceCid": {
      "/": "baga6ea4seaqiaorbflajr4p33w5ixhoighdpnjoltrbnxfh7tgsrxq67fjirqoa"
    },
    "pieceSize": 34359738368,
    "termMin": 1525000,
    "termMax": 1784200,
    "expiration": 4286102,
    "height": 4269784
  },
  {
    "id": 75217405,
    "clientId": 2092888,
    "providerId": 3149598,
    "pieceCid": {
      "/": "baga6ea4seaqn5fi7s6jmxo27d4ie5jtkpcyyvjwqqpeymquzhds5ufiy2esmyii"
    },
    "pieceSize": 34359738368,
    "termMin": 1525000,
    "termMax": 1784200,
    "expiration": 4286102,
    "height": 4269784
  },
  {
    "id": 75217404,
    "clientId": 2092888,
    "providerId": 3149598,
    "pieceCid": {
      "/": "baga6ea4seaqkcmikwuumwsyczxg44dq2gasrjanip3cp6h6tcnznot3tsytfmay"
    },
    "pieceSize": 34359738368,
    "termMin": 1525000,
    "termMax": 1784200,
    "expiration": 4286102,
    "height": 4269784
  },
  {
    "id": 75217403,
    "clientId": 2092888,
    "providerId": 3149598,
    "pieceCid": {
      "/": "baga6ea4seaqiwqit6pj4pwoekt6ytrdawqcwl3hj7hxank7wlieqbr527w25kfy"
    },
    "pieceSize": 34359738368,
    "termMin": 1525000,
    "termMax": 1784200,
    "expiration": 4286102,
    "height": 4269784
  },
  {
    "id": 75217402,
    "clientId": 2092888,
    "providerId": 3149598,
    "pieceCid": {
      "/": "baga6ea4seaqlsxqq5ps4gzigjzmpyvyct7jzjl7ope4uyqyqznhtfdk3ewxqcpi"
    },
    "pieceSize": 34359738368,
    "termMin": 1525000,
    "termMax": 1784200,
    "expiration": 4286103,
    "height": 4269784
  },
  {
    "id": 75217401,
    "clientId": 2092888,
    "providerId": 3149598,
    "pieceCid": {
      "/": "baga6ea4seaqdmb5j4r4bxzymthirhtkade7hcga25gjnfiguvskquogwvwbqcky"
    },
    "pieceSize": 34359738368,
    "termMin": 1525000,
    "termMax": 1784200,
    "expiration": 4286101,
    "height": 4269784
  },
  {
    "id": 75217852,
    "clientId": 2092888,
    "providerId": 3149598,
    "pieceCid": {
      "/": "baga6ea4seaqidwhqlatdkh3ked6l6kbxucqrmave4enfokbvtec5bu2hkickkgq"
    },
    "pieceSize": 34359738368,
    "termMin": 1525000,
    "termMax": 1784200,
    "expiration": 4286106,
    "height": 4269804
  },
  {
    "id": 75217851,
    "clientId": 2092888,
    "providerId": 3149598,
    "pieceCid": {
      "/": "baga6ea4seaqbpr3x62b6tgqswa66bow6724ftyd4g36ocwmrqmf5gmyqtfowojq"
    },
    "pieceSize": 34359738368,
    "termMin": 1525000,
    "termMax": 1784200,
    "expiration": 4286105,
    "height": 4269804
  },
  {
    "id": 75217850,
    "clientId": 2092888,
    "providerId": 3149598,
    "pieceCid": {
      "/": "baga6ea4seaqg5bfudexgrjznshgwyupyh5mgpdzdbotxs7xfbpdo3bli5pln2ji"
    },
    "pieceSize": 34359738368,
    "termMin": 1525000,
    "termMax": 1784200,
    "expiration": 4286105,
    "height": 4269804
  },
  {
    "id": 75217849,
    "clientId": 2092888,
    "providerId": 3149598,
    "pieceCid": {
      "/": "baga6ea4seaqfxbzlyhgtspnnclimn3ydswpobgej5ddg76npx2speac2y23emiy"
    },
    "pieceSize": 34359738368,
    "termMin": 1525000,
    "termMax": 1784200,
    "expiration": 4286105,
    "height": 4269804
  },
  {
    "id": 75217848,
    "clientId": 2092888,
    "providerId": 3149598,
    "pieceCid": {
      "/": "baga6ea4seaqeea63aoackwjouz4ayjzjcsekdwfz6khlctn22mgjhqbwdeoacpa"
    },
    "pieceSize": 34359738368,
    "termMin": 1525000,
    "termMax": 1784200,
    "expiration": 4286104,
    "height": 4269804
  },
  {
    "id": 75217847,
    "clientId": 2092888,
    "providerId": 3149598,
    "pieceCid": {
      "/": "baga6ea4seaqap2ijtj4equ3fuydkpmfwtxr5gy7cbdmyqmvhj22jthpmn5pysga"
    },
    "pieceSize": 34359738368,
    "termMin": 1525000,
    "termMax": 1784200,
    "expiration": 4286104,
    "height": 4269804
  },
  {
    "id": 75217846,
    "clientId": 2092888,
    "providerId": 3149598,
    "pieceCid": {
      "/": "baga6ea4seaqjdvtv5bmzkxvbnrzyfft3tgem7wbbdk24mj7gxtxtwmkouxrdmpy"
    },
    "pieceSize": 34359738368,
    "termMin": 1525000,
    "termMax": 1784200,
    "expiration": 4286104,
    "height": 4269804
  },
  {
    "id": 75217845,
    "clientId": 2092888,
    "providerId": 3149598,
    "pieceCid": {
      "/": "baga6ea4seaqifrhxky3uxpybq353qzqh7eh3qjbnivpixxoczyhmdpf4t6wigfq"
    },
    "pieceSize": 34359738368,
    "termMin": 1525000,
    "termMax": 1784200,
    "expiration": 4286103,
    "height": 4269804
  },
  {
    "id": 75218401,
    "clientId": 2092888,
    "providerId": 3149598,
    "pieceCid": {
      "/": "baga6ea4seaqlyoqxid64x7qkkplpfkfkf4sy7uvc24i7mq7zjliulzrn32i6mpq"
    },
    "pieceSize": 34359738368,
    "termMin": 1525000,
    "termMax": 1784200,
    "expiration": 4286106,
    "height": 4269823
  },
  {
    "id": 75218400,
    "clientId": 2092888,
    "providerId": 3149598,
    "pieceCid": {
      "/": "baga6ea4seaqkjhb2zs2ic77csrw36ntgvwxpakx3ltmnm3mrpxmjboa3zpn6qiy"
    },
    "pieceSize": 34359738368,
    "termMin": 1525000,
    "termMax": 1784200,
    "expiration": 4286106,
    "height": 4269823
  },
  {
    "id": 75218399,
    "clientId": 2092888,
    "providerId": 3149598,
    "pieceCid": {
      "/": "baga6ea4seaqjvuh6whqjiq3ogeeq5r4pk7yj6tvp4a626twbdktemjrbyzz26cy"
    },
    "pieceSize": 34359738368,
    "termMin": 1525000,
    "termMax": 1784200,
    "expiration": 4286105,
    "height": 4269823
  },
  {
    "id": 75218398,
    "clientId": 2092888,
    "providerId": 3149598,
    "pieceCid": {
      "/": "baga6ea4seaqlsxrc5cgt4xqmadyyerig2gkpwz4sc7h3mdno3la4myaa5px3yja"
    },
    "pieceSize": 34359738368,
    "termMin": 1525000,
    "termMax": 1784200,
    "expiration": 4286106,
    "height": 4269823
  },
  {
    "id": 75218397,
    "clientId": 2092888,
    "providerId": 3149598,
    "pieceCid": {
      "/": "baga6ea4seaqbgnyrxqkyvoaqg22fh7okltg77mlv3zwzomocyrmddk6ai65r2oy"
    },
    "pieceSize": 34359738368,
    "termMin": 1525000,
    "termMax": 1784200,
    "expiration": 4286109,
    "height": 4269823
  },
  {
    "id": 75218396,
    "clientId": 2092888,
    "providerId": 3149598,
    "pieceCid": {
      "/": "baga6ea4seaqgw6oise7wvip4l6wq6znapvsgoo2xx3znhxfpjekuxxplm7xvyaa"
    },
    "pieceSize": 34359738368,
    "termMin": 1525000,
    "termMax": 1784200,
    "expiration": 4286108,
    "height": 4269823
  },
  {
    "id": 75218395,
    "clientId": 2092888,
    "providerId": 3149598,
    "pieceCid": {
      "/": "baga6ea4seaqkrichbji2o2gzba27ejfyokd3wq7jhjsxtxggnkkwtvkuj66aypi"
    },
    "pieceSize": 34359738368,
    "termMin": 1525000,
    "termMax": 1784200,
    "expiration": 4286107,
    "height": 4269823
  },
  {
    "id": 75218394,
    "clientId": 2092888,
    "providerId": 3149598,
    "pieceCid": {
      "/": "baga6ea4seaqj4pbhnlsdwcmuyzymyvfs3k3ok54zubolstqvjwz35vry6g5w2gi"
    },
    "pieceSize": 34359738368,
    "termMin": 1525000,
    "termMax": 1784200,
    "expiration": 4286107,
    "height": 4269823
  },
  {
    "id": 75219777,
    "clientId": 2092888,
    "providerId": 3149598,
    "pieceCid": {
      "/": "baga6ea4seaqi7ju77gvjrfw4vkvud7bawvvuj6r325ns7x4hpnfyt5r5vnyfcla"
    },
    "pieceSize": 34359738368,
    "termMin": 1525000,
    "termMax": 1784200,
    "expiration": 4286108,
    "height": 4269863
  },
  {
    "id": 75219776,
    "clientId": 2092888,
    "providerId": 3149598,
    "pieceCid": {
      "/": "baga6ea4seaqissa3n4qsjm4jc63hfdbevwghjeqddwofplhqlm554c53owxbiiq"
    },
    "pieceSize": 34359738368,
    "termMin": 1525000,
    "termMax": 1784200,
    "expiration": 4286108,
    "height": 4269863
  },
  {
    "id": 75219775,
    "clientId": 2092888,
    "providerId": 3149598,
    "pieceCid": {
      "/": "baga6ea4seaqoxktgbbq6h4j7ozceowevmwqj6j55g7es343zt7aszs7mzmeyyfi"
    },
    "pieceSize": 34359738368,
    "termMin": 1525000,
    "termMax": 1784200,
    "expiration": 4286107,
    "height": 4269863
  },
  {
    "id": 75219774,
    "clientId": 2092888,
    "providerId": 3149598,
    "pieceCid": {
      "/": "baga6ea4seaqmc7f63zmz2if76yxlpqp7ill3eq2eby3s3n6bsvl7apzdlxm6gea"
    },
    "pieceSize": 34359738368,
    "termMin": 1525000,
    "termMax": 1784200,
    "expiration": 4286107,
    "height": 4269863
  },
  {
    "id": 75219773,
    "clientId": 2092888,
    "providerId": 3149598,
    "pieceCid": {
      "/": "baga6ea4seaqfedvnmonlmgx6momg3iscahbpvvdymhs4duet6kdvdmjetnxeghq"
    },
    "pieceSize": 34359738368,
    "termMin": 1525000,
    "termMax": 1784200,
    "expiration": 4286109,
    "height": 4269863
  },
  {
    "id": 75219772,
    "clientId": 2092888,
    "providerId": 3149598,
    "pieceCid": {
      "/": "baga6ea4seaqik6rgdbt6gx6ctyuarlymjv3zqmzozipfp4w2zawah6qkwqdtcbq"
    },
    "pieceSize": 34359738368,
    "termMin": 1525000,
    "termMax": 1784200,
    "expiration": 4286108,
    "height": 4269863
  },
  {
    "id": 75219771,
    "clientId": 2092888,
    "providerId": 3149598,
    "pieceCid": {
      "/": "baga6ea4seaqd45beaujjeth6cvph6ktugix4zwleysxuoo6p76jct7i4vk636da"
    },
    "pieceSize": 34359738368,
    "termMin": 1525000,
    "termMax": 1784200,
    "expiration": 4286110,
    "height": 4269863
  },
  {
    "id": 75219770,
    "clientId": 2092888,
    "providerId": 3149598,
    "pieceCid": {
      "/": "baga6ea4seaqjpxom5kpi6zyhxh5nwjsyn6hawtrq74eb6xgi7qkxojvakwfccay"
    },
    "pieceSize": 34359738368,
    "termMin": 1525000,
    "termMax": 1784200,
    "expiration": 4286109,
    "height": 4269863
  },
  {
    "id": 75219996,
    "clientId": 2092888,
    "providerId": 3149598,
    "pieceCid": {
      "/": "baga6ea4seaqhfcbbd4rkkdo6dms3x225mnnwqwxvi6quoi6ikmaa7g7cnmlbufy"
    },
    "pieceSize": 34359738368,
    "termMin": 1525000,
    "termMax": 1784200,
    "expiration": 4286111,
    "height": 4269870
  },
  {
    "id": 75219995,
    "clientId": 2092888,
    "providerId": 3149598,
    "pieceCid": {
      "/": "baga6ea4seaqb54cqu5wo6w7csppa64s2z5zghuc4t44kmihqbpqlsh3m7hl5efa"
    },
    "pieceSize": 34359738368,
    "termMin": 1525000,
    "termMax": 1784200,
    "expiration": 4286110,
    "height": 4269870
  },
  {
    "id": 75219994,
    "clientId": 2092888,
    "providerId": 3149598,
    "pieceCid": {
      "/": "baga6ea4seaqitkjuikbmqy2zuoqfog4iniowfizt6dsz4aop3zgnwo3rd6pnola"
    },
    "pieceSize": 34359738368,
    "termMin": 1525000,
    "termMax": 1784200,
    "expiration": 4286109,
    "height": 4269870
  },
  {
    "id": 75219993,
    "clientId": 2092888,
    "providerId": 3149598,
    "pieceCid": {
      "/": "baga6ea4seaqlrhaz7of4hjufky6piwbwgyemvkovozgvpaopupfa3vwbrfl3kgq"
    },
    "pieceSize": 34359738368,
    "termMin": 1525000,
    "termMax": 1784200,
    "expiration": 4286109,
    "height": 4269870
  },
  {
    "id": 75219992,
    "clientId": 2092888,
    "providerId": 3149598,
    "pieceCid": {
      "/": "baga6ea4seaqmwbxrhm43vv6qx4qgnopeddvq66hbcg6tjtxrekinf6xutkjmafa"
    },
    "pieceSize": 34359738368,
    "termMin": 1525000,
    "termMax": 1784200,
    "expiration": 4286111,
    "height": 4269870
  },
  {
    "id": 75219991,
    "clientId": 2092888,
    "providerId": 3149598,
    "pieceCid": {
      "/": "baga6ea4seaqjurzwodzt3fpvypmtmzr6vq7kh2kv4ms6dxhwqlc46uhdbq6u6ky"
    },
    "pieceSize": 34359738368,
    "termMin": 1525000,
    "termMax": 1784200,
    "expiration": 4286111,
    "height": 4269870
  },
  {
    "id": 75219990,
    "clientId": 2092888,
    "providerId": 3149598,
    "pieceCid": {
      "/": "baga6ea4seaqguhklyj3oimfnnitaglc2kntbcsyvrxh727mnsfmjlvf5zqwaypa"
    },
    "pieceSize": 34359738368,
    "termMin": 1525000,
    "termMax": 1784200,
    "expiration": 4286111,
    "height": 4269870
  },
  {
    "id": 75219989,
    "clientId": 2092888,
    "providerId": 3149598,
    "pieceCid": {
      "/": "baga6ea4seaqnhdh4y4u26lkmhnpgxkp4cstdrqtjr4pbv72wg2udofpczdqnkja"
    },
    "pieceSize": 34359738368,
    "termMin": 1525000,
    "termMax": 1784200,
    "expiration": 4286111,
    "height": 4269870
  },
  {
    "id": 75220534,
    "clientId": 2092888,
    "providerId": 3149598,
    "pieceCid": {
      "/": "baga6ea4seaqejmssacqrzlhh7jddvogty2jpxuzgjatakzjrhmiujbh3rmumuci"
    },
    "pieceSize": 34359738368,
    "termMin": 1525000,
    "termMax": 1784200,
    "expiration": 4286113,
    "height": 4269886
  },
  {
    "id": 75220533,
    "clientId": 2092888,
    "providerId": 3149598,
    "pieceCid": {
      "/": "baga6ea4seaqe4pixuqnze7324syuzd2n7omul7egime42abfbxh52cqfdjqigpq"
    },
    "pieceSize": 34359738368,
    "termMin": 1525000,
    "termMax": 1784200,
    "expiration": 4286112,
    "height": 4269886
  },
  {
    "id": 75220532,
    "clientId": 2092888,
    "providerId": 3149598,
    "pieceCid": {
      "/": "baga6ea4seaqjryu6v47hkfl3atjif4fr6pjvzqeezrtua5b2sfisfi6balfruna"
    },
    "pieceSize": 34359738368,
    "termMin": 1525000,
    "termMax": 1784200,
    "expiration": 4286113,
    "height": 4269886
  },
  {
    "id": 75220531,
    "clientId": 2092888,
    "providerId": 3149598,
    "pieceCid": {
      "/": "baga6ea4seaqlnnrq4v523hpabatjyseutautcwmejjdmrowfta6gbqh23pt7ady"
    },
    "pieceSize": 34359738368,
    "termMin": 1525000,
    "termMax": 1784200,
    "expiration": 4286112,
    "height": 4269886
  },
  {
    "id": 75220530,
    "clientId": 2092888,
    "providerId": 3149598,
    "pieceCid": {
      "/": "baga6ea4seaqecoasa2muljsvg7ww2u6y6i4akpbef2vtvnrvfywibc5e4rpvucy"
    },
    "pieceSize": 34359738368,
    "termMin": 1525000,
    "termMax": 1784200,
    "expiration": 4286112,
    "height": 4269886
  },
  {
    "id": 75220529,
    "clientId": 2092888,
    "providerId": 3149598,
    "pieceCid": {
      "/": "baga6ea4seaqeoo74ivjtpuy7gkxl2pv26o5d3zp63mvweaicqtn7zxpislwzsfi"
    },
    "pieceSize": 34359738368,
    "termMin": 1525000,
    "termMax": 1784200,
    "expiration": 4286112,
    "height": 4269886
  },
  {
    "id": 75220528,
    "clientId": 2092888,
    "providerId": 3149598,
    "pieceCid": {
      "/": "baga6ea4seaqecnkawuvbvoh2ixphutqm4xaicecunbein4vkzd4okjk3bkwsqoi"
    },
    "pieceSize": 34359738368,
    "termMin": 1525000,
    "termMax": 1784200,
    "expiration": 4286110,
    "height": 4269886
  },
  {
    "id": 75220527,
    "clientId": 2092888,
    "providerId": 3149598,
    "pieceCid": {
      "/": "baga6ea4seaqnpdmvd67sjceh4wrlktqgakvmi6dlc4cb4weqlzodkboxdnclgmi"
    },
    "pieceSize": 34359738368,
    "termMin": 1525000,
    "termMax": 1784200,
    "expiration": 4286114,
    "height": 4269886
  },
  {
    "id": 75221288,
    "clientId": 2092888,
    "providerId": 3149598,
    "pieceCid": {
      "/": "baga6ea4seaqolybbdb6xojutc2vqn2hlvawlly3xxfdgbbuc36zrvmamvn6ekdq"
    },
    "pieceSize": 34359738368,
    "termMin": 1525000,
    "termMax": 1784200,
    "expiration": 4286116,
    "height": 4269904
  },
  {
    "id": 75221287,
    "clientId": 2092888,
    "providerId": 3149598,
    "pieceCid": {
      "/": "baga6ea4seaqnnrbhco4qbjljg5vbzxm6oh7nanxss6qq6uxnxmwsbykwrnuvwpq"
    },
    "pieceSize": 34359738368,
    "termMin": 1525000,
    "termMax": 1784200,
    "expiration": 4286114,
    "height": 4269904
  },
  {
    "id": 75221286,
    "clientId": 2092888,
    "providerId": 3149598,
    "pieceCid": {
      "/": "baga6ea4seaqlxxpw6kn2dk3bxxjki2khiojiu3lmxmk2zzwre53cxflzzt4uuaa"
    },
    "pieceSize": 34359738368,
    "termMin": 1525000,
    "termMax": 1784200,
    "expiration": 4286114,
    "height": 4269904
  },
  {
    "id": 75221285,
    "clientId": 2092888,
    "providerId": 3149598,
    "pieceCid": {
      "/": "baga6ea4seaqjtitvf3khkbgr675fnzl2yswtoveoekdcsbu44hmulbld4y4ecky"
    },
    "pieceSize": 34359738368,
    "termMin": 1525000,
    "termMax": 1784200,
    "expiration": 4286114,
    "height": 4269904
  },
  {
    "id": 75221284,
    "clientId": 2092888,
    "providerId": 3149598,
    "pieceCid": {
      "/": "baga6ea4seaqmo6dtpgqm6vckze5i7oexcw3v4icry6aan5lvibukn7sz5stdqiy"
    },
    "pieceSize": 34359738368,
    "termMin": 1525000,
    "termMax": 1784200,
    "expiration": 4286113,
    "height": 4269904
  },
  {
    "id": 75221283,
    "clientId": 2092888,
    "providerId": 3149598,
    "pieceCid": {
      "/": "baga6ea4seaqmwmpzjcd3zsyjl3v7wpnjkowfemfoepldugzbp6j6mygnvcflaly"
    },
    "pieceSize": 34359738368,
    "termMin": 1525000,
    "termMax": 1784200,
    "expiration": 4286113,
    "height": 4269904
  },
  {
    "id": 75221282,
    "clientId": 2092888,
    "providerId": 3149598,
    "pieceCid": {
      "/": "baga6ea4seaqni7lixrc6euuf3gkze7rpowxavb7wwjagnscxbsxga2t6qzpwmlq"
    },
    "pieceSize": 34359738368,
    "termMin": 1525000,
    "termMax": 1784200,
    "expiration": 4286116,
    "height": 4269904
  },
  {
    "id": 75221281,
    "clientId": 2092888,
    "providerId": 3149598,
    "pieceCid": {
      "/": "baga6ea4seaqiycqklk5f4oftunmwiedj3r75rdhcsuftkqfgpkfks2zzkb2csmy"
    },
    "pieceSize": 34359738368,
    "termMin": 1525000,
    "termMax": 1784200,
    "expiration": 4286115,
    "height": 4269904
  }
]